datanomiq_alien/__init__.py
datanomiq_alien-0.0.3.dist-info/LICENCE.txt
datanomiq_alien-0.0.3.dist-info/METADATA
datanomiq_alien-0.0.3.dist-info/WHEEL
datanomiq_alien-0.0.3.dist-info/top_level.txt
datanomiq_alien-0.0.3.dist-info/RECORD
