Metadata-Version: 2.1
Name: datanomiq-alien
Version: 0.0.3
Summary: a pip-installable package example
Home-page: https://github.com/aakashdatanomiqer/datanomiq_alien
Author: Aakash Chugh
Author-email: aakash.chugh@datanomiq.de
License: MIT
Keywords: example
Platform: UNKNOWN
